g2mclient/__init__.py
g2mclient/analyzer.py
g2mclient/client_saml_sso.py
g2mclient/constants.py
g2mclient/runner_base.py
g2mclient/runner_propensity.py
g2mclient/runner_regression.py
g2mclient/utils.py
g2m_api_client-1.2.31.dist-info/METADATA
g2m_api_client-1.2.31.dist-info/WHEEL
g2m_api_client-1.2.31.dist-info/top_level.txt
g2m_api_client-1.2.31.dist-info/RECORD
