Metadata-Version: 2.1
Name: g2m-api-client
Version: 1.2.31
Summary: Analyzr API Client
Home-page: https://analyzr.ai
Author: Analyzr Team
Author-email: support@analyzr.ai
License: Proprietary
Platform: UNKNOWN
Classifier: Programming Language :: Python :: 3
Classifier: Programming Language :: Python :: 3.7
Classifier: Programming Language :: Python :: 3.8
Classifier: Programming Language :: Python :: 3.9
Requires-Dist: scikit-learn
